fsplot/__init__.py
fsplot/fsplot.py
fsplot-0.2.dist-info/LICENSE
fsplot-0.2.dist-info/METADATA
fsplot-0.2.dist-info/WHEEL
fsplot-0.2.dist-info/top_level.txt
fsplot-0.2.dist-info/RECORD
