Metadata-Version: 2.1
Name: fsplot
Version: 0.2
Summary: `fsplot` is a Python library for lightweight visualization of financial market data using SVG.
Home-page: https://github.com/ryanllu/fs-plot
Author: Ryan L.
Author-email: rylu.lubis@gmail.com
Classifier: Programming Language :: Python :: 3
Classifier: License :: OSI Approved :: MIT License
Classifier: Operating System :: OS Independent
Requires-Python: >=3.6
License-File: LICENSE
Requires-Dist: svgwrite (>=1.4.1)
Requires-Dist: numpy (>=1.21.0)
